devtools_ip_lookup/__init__.py
devtools_ip_lookup-1.0.1.dist-info/METADATA
devtools_ip_lookup-1.0.1.dist-info/WHEEL
devtools_ip_lookup-1.0.1.dist-info/top_level.txt
devtools_ip_lookup-1.0.1.dist-info/RECORD
