Metadata-Version: 2.1
Name: devtools_ip_lookup
Version: 1.0.1
Summary: IP address lookup
Home-page: https://devtools.at/tools/ip-lookup
Author: DevTools.at
Author-email: hello@devtools.at
Project-URL: Homepage, https://devtools.at/tools/ip-lookup
Project-URL: Repository, https://github.com/devtools-at/ip-lookup
Classifier: Development Status :: 4 - Beta
Classifier: Intended Audience :: Developers
Classifier: License :: OSI Approved :: MIT License
Classifier: Programming Language :: Python :: 3
Requires-Python: >=3.8
